unionchat
