Metadata-Version: 1.0
Name: unionchat
Version: 0.0.7
Summary: Union chat API wrapper
Home-page: https://github.com/GeoffreyWesthoff/union.py
Author: Geoffrey Westhoff
Author-email: geoffreywesthoff@gmail.com
License: MIT
Platform: UNKNOWN
